dolipy/__init__.py
dolipy/config.py
dolipy/dolibarr.py
dolipy-0.1.2.dist-info/WHEEL
dolipy-0.1.2.dist-info/METADATA
dolipy-0.1.2.dist-info/RECORD
